vxstreamlib.py
vxstreamlib-1.0.0.dist-info/METADATA
vxstreamlib-1.0.0.dist-info/RECORD
vxstreamlib-1.0.0.dist-info/WHEEL
vxstreamlib-1.0.0.dist-info/entry_points.txt
vxstreamlib-1.0.0.dist-info/top_level.txt
