Metadata-Version: 2.1
Name: vxstreamlib
Version: 1.0.0
Summary: A simple library to work with a local instance of VxStream.
Home-page: https://github.com/IntegralDefense/vxstreamlib
Author: John Davison
Author-email: unixfreak0037@gmail.com
License: License :: OSI Approved :: Apache Software License
Keywords: vxstream
Platform: UNKNOWN
Classifier: Development Status :: 3 - Alpha
Classifier: Intended Audience :: Developers
Classifier: Intended Audience :: Information Technology
Classifier: Operating System :: OS Independent
Classifier: License :: OSI Approved :: Apache Software License
Classifier: Programming Language :: Python :: 3 :: Only
Classifier: Programming Language :: Python :: 3
Classifier: Programming Language :: Python :: 3.0
Classifier: Programming Language :: Python :: 3.1
Classifier: Programming Language :: Python :: 3.2
Classifier: Programming Language :: Python :: 3.3
Classifier: Programming Language :: Python :: 3.4
Classifier: Programming Language :: Python :: 3.5
Classifier: Programming Language :: Python :: 3.6
Requires-Dist: requests
